setup.py
labvision/__init__.py
labvision.egg-info/PKG-INFO
labvision.egg-info/SOURCES.txt
labvision.egg-info/dependency_links.txt
labvision.egg-info/requires.txt
labvision.egg-info/top_level.txt
labvision/__deprecated__/__init__.py
labvision/__deprecated__/auto/__init__.py
labvision/__deprecated__/auto/core.py
labvision/__deprecated__/auto/utils.py
labvision/__deprecated__/functional/__init__.py
labvision/__deprecated__/functional/accuracy.py
labvision/__deprecated__/transforms/__init__.py
labvision/__deprecated__/transforms/basic.py
labvision/__deprecated__/transforms/casnet_cvpr_2018.py
labvision/__deprecated__/transforms/utils/__init__.py
labvision/__deprecated__/transforms/utils/chained_transform.py
labvision/__deprecated__/visualize/__init__.py
labvision/__deprecated__/visualize/tensorview.py
labvision/datasets/__init__.py
labvision/datasets/emod.py
labvision/datasets/emotion_roi.py
labvision/datasets/fi.py
labvision/datasets/iaps.py
labvision/datasets/ldl.py
labvision/datasets/utils/__init__.py
labvision/datasets/utils/dataset.py
labvision/datasets/utils/exceptions.py
labvision/dock/__init__.py
labvision/dock/local.py
labvision/dock/server.py
labvision/mods/__init__.py
labvision/mods/accuracy.py
labvision/mods/dataloaders.py
labvision/mods/dry.py
labvision/mods/hash.py
labvision/mods/logger.py
labvision/mods/looper.py
labvision/mods/smooth.py
labvision/mods/step.py
labvision/mods/time.py
labvision/mods/functional/__init__.py
labvision/mods/functional/accuracy.py
labvision/mods/functional/seed.py
labvision/mods/functional/smooth.py
labvision/mods/functional/step.py