Metadata-Version: 1.0
Name: labvision
Version: 0.3.4
Summary: ecust vision lab platform
Home-page: https://github.com/klrc/labvision
Author: klrc
Author-email: sh@mail.ecust.edu.com
License: MIT Licence
Keywords: pip,labvision,ecust
Platform: all
